CHANGES.txt
LICENSE.txt
MANIFEST.in
README.txt
setup.py
js/__init__.py
js.jquery_jgrowl.egg-info/PKG-INFO
js.jquery_jgrowl.egg-info/SOURCES.txt
js.jquery_jgrowl.egg-info/dependency_links.txt
js.jquery_jgrowl.egg-info/entry_points.txt
js.jquery_jgrowl.egg-info/namespace_packages.txt
js.jquery_jgrowl.egg-info/not-zip-safe
js.jquery_jgrowl.egg-info/requires.txt
js.jquery_jgrowl.egg-info/top_level.txt
js/jquery_jgrowl/__init__.py
js/jquery_jgrowl/test_jquery_jgrowl.txt
js/jquery_jgrowl/resources/jquery.jgrowl.css
js/jquery_jgrowl/resources/jquery.jgrowl.js
js/jquery_jgrowl/resources/jquery.jgrowl.min.js