Metadata-Version: 1.0
Name: js.jquery_jgrowl
Version: 1.4.2
Summary: fanstatic jQuery jGrowl.
Home-page: UNKNOWN
Author: Fanstatic Developers
Author-email: fanstatic@googlegroups.com
License: BSD
Platform: UNKNOWN
